conf.py
plotterclassprogra/plotter.py
plotterclassprogra-0.0.5.dist-info/METADATA
plotterclassprogra-0.0.5.dist-info/WHEEL
plotterclassprogra-0.0.5.dist-info/licenses/LICENSE
plotterclassprogra-0.0.5.dist-info/RECORD
