Metadata-Version: 2.1
Name: plotterclassprogra
Version: 0.0.5
Summary: Clase dedicada a poder visualizar diferentes tipos de graficos tras un clustering
Project-URL: Homepage, https://github.com/cristianpazos9/proyecto_programacion
Project-URL: Bug Tracker, https://github.com/cristianpazos9/proyecto_programacion/issues
Author: Manex Bengoa, Cristian Pazos
License: MIT License
License-File: LICENSE
Classifier: License :: OSI Approved :: MIT License
Classifier: Operating System :: OS Independent
Classifier: Programming Language :: Python :: 3
Requires-Python: >=3.9
